Bio_Epidemiology_NER/__init__.py
Bio_Epidemiology_NER/bio_recognizer.py
Bio_Epidemiology_NER-0.1.3.dist-info/METADATA
Bio_Epidemiology_NER-0.1.3.dist-info/WHEEL
Bio_Epidemiology_NER-0.1.3.dist-info/top_level.txt
Bio_Epidemiology_NER-0.1.3.dist-info/RECORD
