Metadata-Version: 2.1
Name: Bio-Epidemiology-NER
Version: 0.1.3
Summary: Recognize bio-medical entities from a text corpus
Home-page: https://github.com/dreji18/biomedicalNER
Author: Deepak John Reji, Shaina Raza, Femi Shajan
Author-email: deepakjohn1994@gmail.com
License: MIT
Classifier: License :: OSI Approved :: MIT License
Classifier: Programming Language :: Python :: 3.6
Classifier: Programming Language :: Python :: 3.7
Classifier: Programming Language :: Python :: 3.8
Classifier: Programming Language :: Python :: 3.9
Requires-Dist: transformers
Requires-Dist: nltk
Requires-Dist: pandas
Requires-Dist: PyMuPDF (==1.20.1)
